seriesmgmtsystem/__init__.py
seriesmgmtsystem/data/bibdb.bib
seriesmgmtsystem/data/captionnames.tex
seriesmgmtsystem/data/sms.sty
seriesmgmtsystem/etc/logging.conf
seriesmgmtsystem/etc/serieManagementSystem-completion.bash
seriesmgmtsystem/etc/seriesmgmtsystem.conf
seriesmgmtsystem/main/__init__.py
seriesmgmtsystem/main/main.py
seriesmgmtsystem/main/mainImpl.py
seriesmgmtsystem/sms/__init__.py
seriesmgmtsystem/sms/serieManagementSystem.py
seriesmgmtsystem/sms/tests/__init__.py
seriesmgmtsystem/sms/tests/calendarEvent_test.py
seriesmgmtsystem/sms/tests/resources/basic.ics
seriesmgmtsystem/utils/LaTeX.py
seriesmgmtsystem/utils/Utils.py
seriesmgmtsystem/utils/ZipUtils.py
seriesmgmtsystem/utils/__init__.py
seriesmgmtsystem-1.1.7.dist-info/DESCRIPTION.rst
seriesmgmtsystem-1.1.7.dist-info/METADATA
seriesmgmtsystem-1.1.7.dist-info/RECORD
seriesmgmtsystem-1.1.7.dist-info/WHEEL
seriesmgmtsystem-1.1.7.dist-info/dependency_links.txt
seriesmgmtsystem-1.1.7.dist-info/entry_points.txt
seriesmgmtsystem-1.1.7.dist-info/metadata.json
seriesmgmtsystem-1.1.7.dist-info/top_level.txt
seriesmgmtsystem-1.1.7.dist-info/zip-safe
