Metadata-Version: 2.0
Name: seriesmgmtsystem
Version: 1.1.7
Summary: Manages Series
Home-page: https://github.com/digsim/seriesManagementSystem
Author: Andreas Ruppen
Author-email: andreas.ruppen@gmail.com
License: Apache
Keywords: students series
Platform: any
Classifier: Development Status :: 5 - Production/Stable
Classifier: Environment :: Console
Classifier: Intended Audience :: Developers
Classifier: Topic :: Utilities
Classifier: License :: OSI Approved :: Apache Software License
Classifier: Operating System :: MacOS :: MacOS X
Classifier: Operating System :: POSIX
Classifier: Operating System :: Microsoft :: Windows
Classifier: Programming Language :: Python :: 2
Classifier: Programming Language :: Python :: 2.6
Classifier: Programming Language :: Python :: 2.7
Classifier: Programming Language :: Python :: 3
Classifier: Programming Language :: Python :: 3.2
Classifier: Programming Language :: Python :: 3.3
Classifier: Programming Language :: Python :: 3.4
Requires-Dist: colorama (==0.3.2)
Requires-Dist: six (==1.10.0)
